MANIFEST.in
README.md
pyproject.toml
requirements.dev.txt
requirements.test.txt
requirements.txt
setup.cfg
setup.py
coqui_trainer.egg-info/PKG-INFO
coqui_trainer.egg-info/SOURCES.txt
coqui_trainer.egg-info/dependency_links.txt
coqui_trainer.egg-info/not-zip-safe
coqui_trainer.egg-info/requires.txt
coqui_trainer.egg-info/top_level.txt
trainer/README.md
trainer/VERSION
trainer/__init__.py
trainer/callbacks.py
trainer/distribute.py
trainer/generic_utils.py
trainer/io.py
trainer/model.py
trainer/torch.py
trainer/trainer.py
trainer/trainer_utils.py
trainer/logging/__init__.py
trainer/logging/aim_logger.py
trainer/logging/base_dash_logger.py
trainer/logging/clearml_logger.py
trainer/logging/console_logger.py
trainer/logging/dummy_logger.py
trainer/logging/mlflow_logger.py
trainer/logging/tensorboard_logger.py
trainer/logging/wandb_logger.py
trainer/utils/__init__.py
trainer/utils/distributed.py