Metadata-Version: 2.1
Name: coqui-trainer
Version: 0.0.5
Summary: General purpose model trainer for PyTorch that is more flexible than it should be, by 🐸Coqui.
Home-page: https://github.com/coqui-ai/Trainer
Author: Eren Gölge
Author-email: egolge@coqui.ai
License: Apache2
Project-URL: Documentation, https://github.com/coqui-ai/Trainer/
Project-URL: Tracker, https://github.com/coqui-ai/Trainer/issues
Project-URL: Repository, https://github.com/coqui-ai/Trainer
Project-URL: Discussions, https://github.com/coqui-ai/Trainer/discussions
Platform: UNKNOWN
Classifier: Environment :: Console
Classifier: Natural Language :: English
Classifier: Development Status :: 3 - Alpha
Classifier: Intended Audience :: Developers
Classifier: License :: OSI Approved :: Apache Software License
Classifier: Operating System :: OS Independent
Classifier: Programming Language :: Python :: 3.6
Classifier: Programming Language :: Python :: 3.7
Classifier: Programming Language :: Python :: 3.8
Classifier: Programming Language :: Python :: 3.9
Requires-Python: >=3.6.0, <3.10
Provides-Extra: dev
Provides-Extra: test
Provides-Extra: all
